dash_editable_div
