Metadata-Version: 1.1
Name: dash-editable-div
Version: 0.0.2
Summary: Editable HTML component for enhanced TextArea components
Home-page: UNKNOWN
Author: Rémi Delbouys <remi.delbouys@laposte.net>
Author-email: UNKNOWN
License: MIT
Platform: UNKNOWN
Classifier: Framework :: Dash
